coco_utils/__init__.py
coco_utils/coco.py
coco_utils/plots.py
coco_utils/schema.py
coco_utils/utils.py
coco_utils-0.0.3.dist-info/LICENSE
coco_utils-0.0.3.dist-info/WHEEL
coco_utils-0.0.3.dist-info/METADATA
coco_utils-0.0.3.dist-info/RECORD
