Metadata-Version: 2.1
Name: coco-utils
Version: 0.0.3
Summary: utility functions for data explorations and metrics calculation on coco data format
Home-page: https://github.com/prakashjayy/coco_utils
Author: Prakash Jay
Author-email: prakashjyy@gmail.com
Requires-Python: >=3.8,<4.0
Classifier: Programming Language :: Python :: 3
Classifier: Programming Language :: Python :: 3.8
Classifier: Programming Language :: Python :: 3.9
Requires-Dist: fastcore (>=1.3.27,<2.0.0)
Requires-Dist: pandas (>=1.3.5,<2.0.0)
Requires-Dist: pycocotools (>=2.0.3,<3.0.0)
Requires-Dist: pydantic (>=1.8.2,<2.0.0)
Requires-Dist: seaborn (>=0.11.2,<0.12.0)
Requires-Dist: torch (>=1.10.1,<2.0.0)
Project-URL: Repository, https://github.com/prakashjayy/coco_utils
